admirarchy/__init__.py
admirarchy/exceptions.py
admirarchy/models.py
admirarchy/toolbox.py
admirarchy/utils.py
admirarchy/locale/en/LC_MESSAGES/django.po
admirarchy/locale/ru/LC_MESSAGES/django.mo
admirarchy/locale/ru/LC_MESSAGES/django.po
admirarchy/static/admin/admirarchy/img/icon_folder.png
admirarchy/static/admin/admirarchy/img/icon_folder_up.png
admirarchy/templates/admin/admirarchy/change_list.html
admirarchy/tests/__init__.py
admirarchy/tests/conftest.py
admirarchy/tests/test_basic.py
admirarchy/tests/testapp/__init__.py
admirarchy/tests/testapp/admin.py
admirarchy/tests/testapp/models.py
admirarchy/tests/testapp/urls.py
django_admirarchy-1.2.2.dist-info/AUTHORS
django_admirarchy-1.2.2.dist-info/LICENSE
django_admirarchy-1.2.2.dist-info/METADATA
django_admirarchy-1.2.2.dist-info/WHEEL
django_admirarchy-1.2.2.dist-info/top_level.txt
django_admirarchy-1.2.2.dist-info/RECORD
